pypies-0.1.1.dist-info/METADATA
pypies-0.1.1.dist-info/WHEEL
pypies/__init__.py
pypies/pypies.cpython-311-x86_64-linux-gnu.so
pypies-0.1.1.dist-info/RECORD
