Metadata-Version: 2.3
Name: pypies
Version: 0.1.1
